isoslam/__init__.py
isoslam/_version.py
isoslam/all_introns_counts_and_info.py
isoslam/default_config.yaml
isoslam/io.py
isoslam/isoslam.py
isoslam/logging.py
isoslam/pipeline_slam_3UIs.py
isoslam/plotting.py
isoslam/processing.py
isoslam/summary.py
isoslam/utils.py
isoslam/validation.py
isoslam/pipeline_slam_3UIs/all_introns_counts_and_info.py
isoslam/pipeline_slam_3UIs/pipeline.yml
isoslam/pipeline_slam_3UIs/summarize_counts.R
isoslam-0.0.0a1.dist-info/licenses/LICENSE
isoslam-0.0.0a1.dist-info/METADATA
isoslam-0.0.0a1.dist-info/WHEEL
isoslam-0.0.0a1.dist-info/entry_points.txt
isoslam-0.0.0a1.dist-info/top_level.txt
isoslam-0.0.0a1.dist-info/RECORD
