Metadata-Version: 2.4
Name: isoslam
Version: 0.0.0a1
Summary: Tools for processing and summarising SLAMSeq experiments.
Author-email: Ian Sudbery <i.sudbery@sheffield.ac.uk>, Jack Riley <jjriley1@sheffield.ac.uk>, Neil Shephard <n.shephard@sheffield.ac.uk>
License: MIT License
Project-URL: Source, https://github.com/sudlab/IsoSLAM
Project-URL: Bug_Tracker, https://github.com/sudlab/IsoSLAM/issues
Project-URL: Documentation, https://sudlab.github.io/IsoSLAM
Keywords: bioinformatics,rna,sequence alignment,slamseq
Classifier: Programming Language :: Python :: 3
Classifier: Programming Language :: Python :: 3.10
Classifier: Programming Language :: Python :: 3.11
Classifier: Programming Language :: Python :: 3.12
Classifier: Natural Language :: English
Classifier: Operating System :: OS Independent
Classifier: Intended Audience :: Science/Research
Classifier: License :: OSI Approved :: GNU Lesser General Public License v3 (LGPLv3)
Classifier: Topic :: Scientific/Engineering :: Bio-Informatics
Requires-Python: >=3.10
License-File: LICENSE
Requires-Dist: apsw
Requires-Dist: gevent
Requires-Dist: loguru
Requires-Dist: matplotlib
Requires-Dist: numpy
Requires-Dist: pandas
Requires-Dist: polars
Requires-Dist: pysam
Requires-Dist: ruamel.yaml
Requires-Dist: schema
Requires-Dist: sqlalchemy
Provides-Extra: tests
Requires-Dist: filetype; extra == "tests"
Requires-Dist: pyarrow; extra == "tests"
Requires-Dist: pytest; extra == "tests"
Requires-Dist: pytest-cov; extra == "tests"
Requires-Dist: pytest-github-actions-annotate-failures; extra == "tests"
Requires-Dist: pytest-mpl; extra == "tests"
Requires-Dist: pytest-regtest; extra == "tests"
Requires-Dist: pytest-testmon; extra == "tests"
Requires-Dist: syrupy; extra == "tests"
Provides-Extra: docs
Requires-Dist: mkdocs; extra == "docs"
Requires-Dist: mkdocs-material; extra == "docs"
Requires-Dist: mkdocs-mermaid2-plugin; extra == "docs"
Requires-Dist: mkdocstrings[python]; extra == "docs"
Provides-Extra: dev
Requires-Dist: black; extra == "dev"
Requires-Dist: ipython; extra == "dev"
Requires-Dist: mypy; extra == "dev"
Requires-Dist: parquet_tools; extra == "dev"
Requires-Dist: pre-commit; extra == "dev"
Requires-Dist: pylint; extra == "dev"
Requires-Dist: pyupgrade; extra == "dev"
Requires-Dist: pytest-durations; extra == "dev"
Requires-Dist: pytest-icdiff; extra == "dev"
Requires-Dist: pytest-testmon; extra == "dev"
Requires-Dist: pytest-xdist; extra == "dev"
Requires-Dist: snakeviz; extra == "dev"
Provides-Extra: pypi
Requires-Dist: build; extra == "pypi"
Requires-Dist: setuptools_scm[toml]; extra == "pypi"
Requires-Dist: wheel; extra == "pypi"
Dynamic: license-file
